setup.py
sphinxcontrib/__init__.py
sphinxcontrib.twitter.egg-info/PKG-INFO
sphinxcontrib.twitter.egg-info/SOURCES.txt
sphinxcontrib.twitter.egg-info/dependency_links.txt
sphinxcontrib.twitter.egg-info/namespace_packages.txt
sphinxcontrib.twitter.egg-info/requires.txt
sphinxcontrib.twitter.egg-info/top_level.txt
sphinxcontrib/twitter/__init__.py
sphinxcontrib/twitter/errors.py
sphinxcontrib/twitter/tweet.py
sphinxcontrib/twitter/user.py