Metadata-Version: 1.1
Name: sphinxcontrib.twitter
Version: 0.2.1
Summary: embedding twitter's tweet in sphinx
Home-page: https://github.com/shomah4a/sphinx-tweet-embed
Author: @shomah4a
Author-email: UNKNOWN
License: LGPLv3
Platform: UNKNOWN
Classifier: Programming Language :: Python
Classifier: Development Status :: 4 - Beta
Classifier: License :: OSI Approved :: GNU Lesser General Public License v3 (LGPLv3)
Classifier: Programming Language :: Python :: 2
Classifier: Programming Language :: Python :: 2.6
Classifier: Programming Language :: Python :: 2.7
Classifier: Programming Language :: Python :: 3
Classifier: Programming Language :: Python :: 3.3
Classifier: Topic :: Software Development :: Documentation
